setup.cfg
setup.py
ahsay/__init__.py
ahsay/api.py
ahsay/example.py
ahsay.egg-info/PKG-INFO
ahsay.egg-info/SOURCES.txt
ahsay.egg-info/dependency_links.txt
ahsay.egg-info/requires.txt
ahsay.egg-info/top_level.txt