Metadata-Version: 1.1
Name: ahsay
Version: 0.2.0
Summary: A simple requests wrapper for the Ahsay API
Home-page: https://github.com/koddsson/ahsay-python-api
Author: Kristjan Oddsson
Author-email: koddsson@gmail.com
License: UNKNOWN
Download-URL: https://github.com/koddsson/ahsay-python-api/tarball/0.2.0
Keywords: ahsay,backup,api
Platform: UNKNOWN
